dora_camera_realsense/main.py
dora_camera_realsense-0.0.1.dist-info/licenses/LICENSE
dora_camera_realsense-0.0.1.dist-info/METADATA
dora_camera_realsense-0.0.1.dist-info/WHEEL
dora_camera_realsense-0.0.1.dist-info/entry_points.txt
dora_camera_realsense-0.0.1.dist-info/top_level.txt
dora_camera_realsense-0.0.1.dist-info/RECORD
