Metadata-Version: 2.4
Name: dora-camera-realsense
Version: 0.0.1
Author-email: Xiang Yang <ryu-yang@qq.com>, Runtian Xu <xuruntian03@163.com>
Requires-Python: <3.11,>=3.9
License-File: LICENSE
Requires-Dist: dora-rs<0.4.0,>=0.3.11
Requires-Dist: opencv-python
Requires-Dist: pyrealsense2
Requires-Dist: numpy
Provides-Extra: view
Requires-Dist: dora-rs-cli; extra == "view"
Requires-Dist: opencv-plot; extra == "view"
Dynamic: license-file
